argmaxima/version.py
argmaxima-0.0.1.dist-info/WHEEL
argmaxima-0.0.1.dist-info/METADATA
argmaxima-0.0.1.dist-info/RECORD
