Metadata-Version: 2.1
Name: argmaxima
Version: 0.0.1
Summary: ARGMAX
Home-page: https://www.sigforge.com
License: BSD-3
Author: Michele Dallachiesa
Author-email: michele.dallachiesa@sigforge.com
Requires-Python: >=3.10.0,<3.13.0
Classifier: Development Status :: 3 - Alpha
Classifier: Intended Audience :: Science/Research
Classifier: License :: OSI Approved
Classifier: License :: Other/Proprietary License
Classifier: Programming Language :: Python :: 3
Classifier: Programming Language :: Python :: 3.10
Classifier: Programming Language :: Python :: 3.11
Project-URL: Repository, https://github.com/elehcimd/
